fastapi_security_middleware/__init__.py
fastapi_security_middleware/headers.py
fastapi_security_middleware/middleware.py
fastapi_security_middleware/rules.py
fastapi_security_middleware/config/__init__.py
fastapi_security_middleware/config/load.py
tests/__init__.py
tests/test_middleware.py
fastapi_security_middleware-0.1.3.dist-info/LICENSE
fastapi_security_middleware-0.1.3.dist-info/METADATA
fastapi_security_middleware-0.1.3.dist-info/WHEEL
fastapi_security_middleware-0.1.3.dist-info/top_level.txt
fastapi_security_middleware-0.1.3.dist-info/RECORD
