Metadata-Version: 2.1
Name: fastapi_security_middleware
Version: 0.1.3
Summary: Simple security middleware for FastAPI
Home-page: https://github.com/kaiqui/fastapi_security_middleware
Author: kaiqui
Author-email: kaiqui82@gmail.com
Classifier: Programming Language :: Python :: 3
Classifier: License :: OSI Approved :: MIT License
Classifier: Operating System :: OS Independent
Requires-Python: >=3.9
License-File: LICENSE
Requires-Dist: fastapi
Requires-Dist: starlette
Requires-Dist: httpx
Requires-Dist: pyyaml
Requires-Dist: loguru
